README.md
setup.py
requests_paginator/__init__.py
requests_paginator.egg-info/PKG-INFO
requests_paginator.egg-info/SOURCES.txt
requests_paginator.egg-info/dependency_links.txt
requests_paginator.egg-info/requires.txt
requests_paginator.egg-info/top_level.txt