Metadata-Version: 2.1
Name: requests-paginator
Version: 0.2.0
Summary: A generator for iterating over paginated API responses
Home-page: https://github.com/chris48s/requests-paginator
Author: chris48s
License: MIT
Platform: UNKNOWN
Classifier: License :: OSI Approved :: MIT License
Classifier: Programming Language :: Python
Classifier: Programming Language :: Python :: 3
